spikesorters/__init__.py
spikesorters/basesorter.py
spikesorters/launcher.py
spikesorters/sorter_tools.py
spikesorters/sorterlist.py
spikesorters/version.py
spikesorters/combinato/__init__.py
spikesorters/combinato/combinato.py
spikesorters/hdsort/__init__.py
spikesorters/hdsort/hdsort.py
spikesorters/hdsort/hdsort_config.m
spikesorters/hdsort/hdsort_master.m
spikesorters/herdingspikes/__init__.py
spikesorters/herdingspikes/herdingspikes.py
spikesorters/ironclust/__init__.py
spikesorters/ironclust/ironclust.py
spikesorters/kilosort/__init__.py
spikesorters/kilosort/kilosort.py
spikesorters/kilosort/kilosort_channelmap.m
spikesorters/kilosort/kilosort_config.m
spikesorters/kilosort/kilosort_master.m
spikesorters/kilosort2/__init__.py
spikesorters/kilosort2/kilosort2.py
spikesorters/kilosort2/kilosort2_channelmap.m
spikesorters/kilosort2/kilosort2_config.m
spikesorters/kilosort2/kilosort2_master.m
spikesorters/kilosort2_5/__init__.py
spikesorters/kilosort2_5/kilosort2_5.py
spikesorters/kilosort2_5/kilosort2_5_channelmap.m
spikesorters/kilosort2_5/kilosort2_5_config.m
spikesorters/kilosort2_5/kilosort2_5_master.m
spikesorters/kilosort3/__init__.py
spikesorters/kilosort3/kilosort3.py
spikesorters/kilosort3/kilosort3_channelmap.m
spikesorters/kilosort3/kilosort3_config.m
spikesorters/kilosort3/kilosort3_master.m
spikesorters/klusta/__init__.py
spikesorters/klusta/config_default.prm
spikesorters/klusta/klusta.py
spikesorters/mountainsort4/__init__.py
spikesorters/mountainsort4/mountainsort4.py
spikesorters/spyking_circus/__init__.py
spikesorters/spyking_circus/config_default.params
spikesorters/spyking_circus/spyking_circus.py
spikesorters/tests/__init__.py
spikesorters/tests/common_tests.py
spikesorters/tests/test_herdingspikes.py
spikesorters/tests/test_ironclust.py
spikesorters/tests/test_kilosort.py
spikesorters/tests/test_kilosort2.py
spikesorters/tests/test_klusta.py
spikesorters/tests/test_launcher.py
spikesorters/tests/test_mountainsort4.py
spikesorters-0.4.5.dist-info/LICENSE
spikesorters-0.4.5.dist-info/METADATA
spikesorters-0.4.5.dist-info/WHEEL
spikesorters-0.4.5.dist-info/top_level.txt
spikesorters-0.4.5.dist-info/RECORD
