Metadata-Version: 2.1
Name: spikesorters
Version: 0.4.5
Summary: Python wrappers for popular spike sorters
Home-page: https://github.com/SpikeInterface/spikesorters
Author: Alessio Buccino, Cole Hurwitz, Samuel Garcia, Jeremy Magland, Matthias Hennig
Author-email: alessiop.buccino@gmail.com
License: UNKNOWN
Platform: UNKNOWN
Classifier: Programming Language :: Python :: 3
Classifier: License :: OSI Approved :: Apache Software License
Classifier: Operating System :: OS Independent
Requires-Dist: numpy
Requires-Dist: spikeextractors (>=0.9.7)
Requires-Dist: spiketoolkit (>=0.7.6)
Requires-Dist: requests
